{"cameraMode":{"drawMode":0,"name":"Shaded","section":"Shading Mode"},"sceneLighting":true,"audioPlay":false,"sceneViewState":{"m_AlwaysRefresh":false,"showFog":true,"showSkybox":true,"showFlares":true,"showImageEffects":true,"showParticleSystems":true,"showVisualEffectGraphs":true,"m_FxEnabled":true},"in2DMode":false,"pivot":{"x":-3.8028483390808107,"y":0.2309410125017166,"z":9.1671781539917},"rotation":{"x":0.2897837162017822,"y":-0.14035308361053468,"z":0.042992766946554187,"w":0.9457904100418091},"size":6.646200656890869,"orthographic":false}